repoze.zcml-1.1-py3.8-nspkg.pth
repoze/zcml/__init__.py
repoze/zcml/_compat.py
repoze/zcml/meta.zcml
repoze/zcml/tests.py
repoze.zcml-1.1.dist-info/LICENSE.txt
repoze.zcml-1.1.dist-info/METADATA
repoze.zcml-1.1.dist-info/WHEEL
repoze.zcml-1.1.dist-info/entry_points.txt
repoze.zcml-1.1.dist-info/namespace_packages.txt
repoze.zcml-1.1.dist-info/top_level.txt
repoze.zcml-1.1.dist-info/RECORD
