Metadata-Version: 2.1
Name: repoze.zcml
Version: 1.1
Summary: Core directives for use in ZCML-based applications
Home-page: http://www.repoze.org
Author: Agendaless Consulting
Author-email: repoze-dev@lists.repoze.org
License: BSD-derived (http://www.repoze.org/LICENSE.txt)
Keywords: zope zcml component architecture
Platform: UNKNOWN
Classifier: Development Status :: 3 - Alpha
Classifier: Intended Audience :: Developers
Classifier: Programming Language :: Python
Classifier: Programming Language :: Python :: 2
Classifier: Programming Language :: Python :: 2.7
Classifier: Programming Language :: Python :: 3
Classifier: Programming Language :: Python :: 3.5
Classifier: Programming Language :: Python :: 3.6
Classifier: Programming Language :: Python :: 3.7
Classifier: Programming Language :: Python :: 3.8
Classifier: Programming Language :: Python :: Implementation :: CPython
Requires-Dist: setuptools
Requires-Dist: zope.component (>=3.5.0)
Requires-Dist: zope.configuration
Provides-Extra: testing
Requires-Dist: setuptools ; extra == 'testing'
Requires-Dist: zope.component (>=3.5.0) ; extra == 'testing'
Requires-Dist: zope.configuration ; extra == 'testing'
Requires-Dist: zope.testing ; extra == 'testing'
Requires-Dist: nose ; extra == 'testing'
Requires-Dist: coverage ; extra == 'testing'
